weheat/__init__.py
weheat/api_client.py
weheat/api_response.py
weheat/configuration.py
weheat/exceptions.py
weheat/py.typed
weheat/rest.py
weheat/abstractions/__init__.py
weheat/abstractions/discovery.py
weheat/abstractions/heat_pump.py
weheat/abstractions/user.py
weheat/api/__init__.py
weheat/api/energy_log_api.py
weheat/api/heat_pump_api.py
weheat/api/heat_pump_log_api.py
weheat/api/user_api.py
weheat/models/__init__.py
weheat/models/boiler_type.py
weheat/models/device_state.py
weheat/models/dhw_type.py
weheat/models/energy_view_dto.py
weheat/models/heat_pump_log_view_dto.py
weheat/models/heat_pump_model.py
weheat/models/heat_pump_status_enum.py
weheat/models/pagination_metadata.py
weheat/models/raw_heat_pump_log_dto.py
weheat/models/raw_heatpump_log_and_is_online_dto.py
weheat/models/read_all_heat_pump_dto.py
weheat/models/read_all_heat_pump_dto_paged_response.py
weheat/models/read_heat_pump_dto.py
weheat/models/read_user_dto.py
weheat/models/read_user_me_dto.py
weheat/models/role.py
weheat/models/total_energy_aggregate.py
weheat-2026.1.25.dist-info/licenses/LICENSE
weheat-2026.1.25.dist-info/METADATA
weheat-2026.1.25.dist-info/WHEEL
weheat-2026.1.25.dist-info/top_level.txt
weheat-2026.1.25.dist-info/RECORD
